PythonExtensions/Core/Constants.py
PythonExtensions/Core/Dates.py
PythonExtensions/Core/Debug.py
PythonExtensions/Core/Exceptions.py
PythonExtensions/Core/Files.py
PythonExtensions/Core/HID_BUFFER.py
PythonExtensions/Core/Json.py
PythonExtensions/Core/Logging.py
PythonExtensions/Core/Misc.py
PythonExtensions/Core/Names.py
PythonExtensions/Core/Threads.py
PythonExtensions/Core/__init__.py
PythonExtensions/Models/MultiDictModel.py
PythonExtensions/Models/__init__.py
PythonExtensions/Setup/Classifiers.json
PythonExtensions/Setup/Classifiers.py
PythonExtensions/Setup/__init__.py
PythonExtensions/Setup/build_classifiers.py
PythonExtensions/Setup/classifiers.txt
PythonExtensions/tk/AioTkinter.py
PythonExtensions/tk/Base.py
PythonExtensions/tk/Custom.py
PythonExtensions/tk/Enumerations.py
PythonExtensions/tk/Events.py
PythonExtensions/tk/KeyBoard.py
PythonExtensions/tk/Roots.py
PythonExtensions/tk/Style.py
PythonExtensions/tk/Themed.py
PythonExtensions/tk/Widgets.py
PythonExtensions/tk/__init__.py
PythonExtensions/tk/tkNamedColor/__init__.py
PythonExtensions/tk/tkNamedColor/colors.png
PythonExtensions-2.2.6.dist-info/LICENSE.md
PythonExtensions-2.2.6.dist-info/METADATA
PythonExtensions-2.2.6.dist-info/WHEEL
PythonExtensions-2.2.6.dist-info/top_level.txt
PythonExtensions-2.2.6.dist-info/RECORD
