Metadata-Version: 2.1
Name: PythonExtensions
Version: 2.2.6
Summary: Strongly typed classes with multiple built in helper functions to speed up development.
Home-page: https://github.com/Jakar510/PythonExtensions
Author: Tyler Stegmaier
Author-email: tyler.stegmaier.510@gmail.com
Maintainer: Tyler Stegmaier
Maintainer-email: tyler.stegmaier.510@gmail.com
License: MIT
Keywords: PythonExtensions Debug Files async Setup Tkinter Extensions tk ttk tkinter
Platform: UNKNOWN
Classifier: Development Status :: 3 - Alpha
Classifier: Intended Audience :: Developers
Classifier: Intended Audience :: Education
Classifier: Topic :: Software Development :: Build Tools
Classifier: Typing :: Typed
Classifier: License :: OSI Approved :: MIT License
Classifier: Operating System :: MacOS
Classifier: Operating System :: Microsoft :: Windows
Classifier: Operating System :: Microsoft :: Windows :: Windows 10
Classifier: Operating System :: POSIX :: Linux
Classifier: Programming Language :: Python
Classifier: Programming Language :: Python :: 3 :: Only
Classifier: Programming Language :: Python :: 3.9
License-File: LICENSE.md
Requires-Dist: pillow (>=8.4.0)
Requires-Dist: tk-html-widgets (>=0.4.0)
Requires-Dist: requests (>=2.26.0)
Requires-Dist: psutil (>=5.8.0)
Requires-Dist: multidict (>=5.2.0)
Requires-Dist: cryptography (>=36.0.0)
Requires-Dist: attr (>=0.3.1)
Requires-Dist: cattrs (>=1.9.0)
Requires-Dist: aiofiles (>=0.8.0)
Requires-Dist: prettyprinter (>=0.18.0)
Requires-Dist: aiohttp (>=3.8.1)
Requires-Dist: yarl (>=1.7.2)
Requires-Dist: python-dateutil (>=2.8.2)
